aladdinsdk/__init__.py
aladdinsdk/adc/__init__.py
aladdinsdk/adc/client.py
aladdinsdk/api/__init__.py
aladdinsdk/api/client.py
aladdinsdk/api/registry.py
aladdinsdk/api/codegen/__init__.py
aladdinsdk/api/codegen/codegen_allow_list.yaml
aladdinsdk/api/codegen/platform/infrastructure/token/v1/TokenAPI/__init__.py
aladdinsdk/api/codegen/platform/infrastructure/token/v1/TokenAPI/api_client.py
aladdinsdk/api/codegen/platform/infrastructure/token/v1/TokenAPI/api_response.py
aladdinsdk/api/codegen/platform/infrastructure/token/v1/TokenAPI/configuration.py
aladdinsdk/api/codegen/platform/infrastructure/token/v1/TokenAPI/exceptions.py
aladdinsdk/api/codegen/platform/infrastructure/token/v1/TokenAPI/rest.py
aladdinsdk/api/codegen/platform/infrastructure/token/v1/TokenAPI/swagger.json
aladdinsdk/api/codegen/platform/infrastructure/token/v1/TokenAPI/api/__init__.py
aladdinsdk/api/codegen/platform/infrastructure/token/v1/TokenAPI/api/default_token_api.py
aladdinsdk/api/codegen/platform/infrastructure/token/v1/TokenAPI/models/__init__.py
aladdinsdk/api/codegen/platform/infrastructure/token/v1/TokenAPI/models/any.py
aladdinsdk/api/codegen/platform/infrastructure/token/v1/TokenAPI/models/rpc_status.py
aladdinsdk/api/codegen/platform/infrastructure/token/v1/TokenAPI/models/token_api_generate_authorization_url400_response.py
aladdinsdk/api/codegen/platform/infrastructure/token/v1/TokenAPI/models/v1_authorization_url.py
aladdinsdk/api/codegen/platform/infrastructure/token/v1/TokenAPI/models/v1_check_token_exists_response.py
aladdinsdk/api/codegen/platform/infrastructure/token/v1/TokenAPI/models/v1_token.py
aladdinsdk/api/codegen/reference_architecture/demo/train_journey/v1/TrainJourneyAPI/__init__.py
aladdinsdk/api/codegen/reference_architecture/demo/train_journey/v1/TrainJourneyAPI/api_client.py
aladdinsdk/api/codegen/reference_architecture/demo/train_journey/v1/TrainJourneyAPI/api_response.py
aladdinsdk-2.0.0b7.dist-info/licenses/LICENSE
aladdinsdk-2.0.0b7.dist-info/METADATA
aladdinsdk-2.0.0b7.dist-info/WHEEL
aladdinsdk-2.0.0b7.dist-info/entry_points.txt
aladdinsdk-2.0.0b7.dist-info/top_level.txt
aladdinsdk-2.0.0b7.dist-info/RECORD
