Metadata-Version: 2.4
Name: aladdinsdk
Version: 2.0.0b7
Summary: AladdinSDK
Author-email: Vedant Naik <naik.vedant@gmail.com>
Classifier: Programming Language :: Python :: 3
Classifier: License :: OSI Approved :: Apache Software License
Classifier: Operating System :: OS Independent
Requires-Python: >=3.9
License-File: LICENSE
Requires-Dist: aenum~=3.1.15
Requires-Dist: cryptography~=42.0.5
Requires-Dist: dynaconf~=3.2.3
Requires-Dist: jsonpath-ng~=1.6.1
Requires-Dist: openpyxl~=3.1.2
Requires-Dist: pandas~=2.2.1
Requires-Dist: pick~=2.2.0
Requires-Dist: pydantic~=1.10.12
Requires-Dist: python_dateutil~=2.9.0
Requires-Dist: pyopenssl~=24.0.0
Requires-Dist: PyYAML~=6.0.1
Requires-Dist: snowflake-connector-python[pandas]~=3.15.0
Requires-Dist: snowflake-snowpark-python[pandas]~=1.31.1
Requires-Dist: requests~=2.31.0
Requires-Dist: requests-oauthlib~=2.0.0
Requires-Dist: tenacity~=8.2.3
Requires-Dist: urllib3~=1.26.16
Requires-Dist: boto3~=1.35.83
Dynamic: license-file
